pythonipsumlorem/__init__.py
pythonipsumlorem-0.1.0.dist-info/METADATA
pythonipsumlorem-0.1.0.dist-info/WHEEL
pythonipsumlorem-0.1.0.dist-info/top_level.txt
pythonipsumlorem-0.1.0.dist-info/RECORD
