Metadata-Version: 2.4
Name: pythonipsumlorem
Version: 0.1.0
Summary: A simple Python module that adds a variable and a Lorem Ipsum function.
Author: Arran Hewitt
Classifier: Programming Language :: Python :: 3
Classifier: Operating System :: OS Independent
Classifier: License :: OSI Approved :: MIT License
Requires-Python: >=3.7
Dynamic: author
Dynamic: classifier
Dynamic: description
Dynamic: description-content-type
Dynamic: requires-python
Dynamic: summary
